bbcodepy/__init__.py
bbcodepy/parser.py
bbcodepy/renderer.py
bbcodepy/tags.py
bbcodepy_cyntara-0.1.0.dist-info/LICENSE
bbcodepy_cyntara-0.1.0.dist-info/METADATA
bbcodepy_cyntara-0.1.0.dist-info/WHEEL
bbcodepy_cyntara-0.1.0.dist-info/top_level.txt
bbcodepy_cyntara-0.1.0.dist-info/RECORD
